{"1998-05-05T20:00:00.000Z": {"htmlhits": 3379, "httpmethod": {"CONNECT": 0, "DELETE": 0, "GET": 62800, "HEAD": 14, "OPTIONS": 0, "OTHER": 0, "POST": 188, "PUT": 0, "TRACE": 0}, "httpstatus": {"-xx": 0, "1xx": 0, "2xx": 56481, "3xx": 6467, "4xx": 54, "5xx": 0}, "httpversion": {"HTTP/0.9": 0, "HTTP/1.0": 50886, "HTTP/1.1": 12115, "HTTP/X.X": 1}, "tothits": 63002, "transferred_bytes": 375521797, "uusers": 1578}, "1998-05-05T21:00:00.000Z": {"htmlhits": 2067, "httpmethod": {"CONNECT": 0, "DELETE": 0, "GET": 40296, "HEAD": 11, "OPTIONS": 0, "OTHER": 0, "POST": 68, "PUT": 0, "TRACE": 0}, "httpstatus": {"-xx": 0, "1xx": 0, "2xx": 35815, "3xx": 4533, "4xx": 27, "5xx": 0}, "httpversion": {"HTTP/0.9": 0, "HTTP/1.0": 32633, "HTTP/1.1": 7741, "HTTP/X.X": 1}, "tothits": 40375, "transferred_bytes": 225499869, "uusers": 1217}, "1998-05-05T22:00:00.000Z": {"htmlhits": 2633, "httpmethod": {"CONNECT": 0, "DELETE": 0, "GET": 51858, "HEAD": 17, "OPTIONS": 0, "OTHER": 0, "POST": 164, "PUT": 0, "TRACE": 0}, "httpstatus": {"-xx": 0, "1xx": 0, "2xx": 46686, "3xx": 5250, "4xx": 98, "5xx": 5}, "httpversion": {"HTTP/0.9": 0, "HTTP/1.0": 40993, "HTTP/1.1": 11042, "HTTP/X.X": 4}, "tothits": 52039, "transferred_bytes": 384929069, "uusers": 1478}, "1998-05-05T23:00:00.000Z": {"htmlhits": 2404, "httpmethod": {"CONNECT": 0, "DELETE": 0, "GET": 47914, "HEAD": 10, "OPTIONS": 0, "OTHER": 0, "POST": 137, "PUT": 0, "TRACE": 0}, "httpstatus": {"-xx": 0, "1xx": 0, "2xx": 43404, "3xx": 4621, "4xx": 36, "5xx": 0}, "httpversion": {"HTTP/0.9": 0, "HTTP/1.0": 39333, "HTTP/1.1": 8728, "HTTP/X.X": 0}, "tothits": 48061, "transferred_bytes": 339433289, "uusers": 1371}, "1998-05-06T00:00:00.000Z": {"htmlhits": 2106, "httpmethod": {"CONNECT": 0, "DELETE": 0, "GET": 42812, "HEAD": 16, "OPTIONS": 0, "OTHER": 0, "POST": 148, "PUT": 0, "TRACE": 0}, "httpstatus": {"-xx": 0, "1xx": 0, "2xx": 38591, "3xx": 4364, "4xx": 21, "5xx": 0}, "httpversion": {"HTTP/0.9": 0, "HTTP/1.0": 34047, "HTTP/1.1": 8929, "HTTP/X.X": 0}, "tothits": 42976, "transferred_bytes": 301775059, "uusers": 1292}, "1998-05-06T01:00:00.000Z": {"htmlhits": 2428, "httpmethod": {"CONNECT": 0, "DELETE": 0, "GET": 49341, "HEAD": 23, "OPTIONS": 0, "OTHER": 0, "POST": 73, "PUT": 0, "TRACE": 0}, "httpstatus": {"-xx": 3, "1xx": 0, "2xx": 43776, "3xx": 5617, "4xx": 41, "5xx": 0}, "httpversion": {"HTTP/0.9": 0, "HTTP/1.0": 40357, "HTTP/1.1": 9077, "HTTP/X.X": 3}, "tothits": 49437, "transferred_bytes": 330819532, "uusers": 1290}, "1998-05-06T02:00:00.000Z": {"htmlhits": 2155, "httpmethod": {"CONNECT": 0, "DELETE": 0, "GET": 40900, "HEAD": 13, "OPTIONS": 0, "OTHER": 0, "POST": 62, "PUT": 0, "TRACE": 0}, "httpstatus": {"-xx": 0, "1xx": 0, "2xx": 36004, "3xx": 4921, "4xx": 50, "5xx": 0}, "httpversion": {"HTTP/0.9": 0, "HTTP/1.0": 33560, "HTTP/1.1": 7415, "HTTP/X.X": 0}, "tothits": 40975, "transferred_bytes": 393264588, "uusers": 1268}, "1998-05-06T03:00:00.000Z": {"htmlhits": 2196, "httpmethod": {"CONNECT": 0, "DELETE": 0, "GET": 41843, "HEAD": 22, "OPTIONS": 0, "OTHER": 0, "POST": 45, "PUT": 0, "TRACE": 0}, "httpstatus": {"-xx": 0, "1xx": 0, "2xx": 37196, "3xx": 4662, "4xx": 50, "5xx": 2}, "httpversion": {"HTTP/0.9": 0, "HTTP/1.0": 34951, "HTTP/1.1": 6958, "HTTP/X.X": 1}, "tothits": 41910, "transferred_bytes": 340193304, "uusers": 1238}, "1998-05-06T04:00:00.000Z": {"htmlhits": 2747, "httpmethod": {"CONNECT": 0, "DELETE": 0, "GET": 49648, "HEAD": 17, "OPTIONS": 0, "OTHER": 0, "POST": 92, "PUT": 0, "TRACE": 0}, "httpstatus": {"-xx": 0, "1xx": 0, "2xx": 43542, "3xx": 6185, "4xx": 30, "5xx": 0}, "httpversion": {"HTTP/0.9": 0, "HTTP/1.0": 41643, "HTTP/1.1": 8114, "HTTP/X.X": 0}, "tothits": 49757, "transferred_bytes": 467638824, "uusers": 1416}, "1998-05-06T05:00:00.000Z": {"htmlhits": 3830, "httpmethod": {"CONNECT": 0, "DELETE": 0, "GET": 68069, "HEAD": 13, "OPTIONS": 0, "OTHER": 0, "POST": 132, "PUT": 0, "TRACE": 0}, "httpstatus": {"-xx": 0, "1xx": 0, "2xx": 57919, "3xx": 10219, "4xx": 74, "5xx": 2}, "httpversion": {"HTTP/0.9": 0, "HTTP/1.0": 56556, "HTTP/1.1": 11657, "HTTP/X.X": 1}, "tothits": 68214, "transferred_bytes": 501070918, "uusers": 1739}, "1998-05-06T06:00:00.000Z": {"htmlhits": 4005, "httpmethod": {"CONNECT": 0, "DELETE": 0, "GET": 72477, "HEAD": 18, "OPTIONS": 0, "OTHER": 0, "POST": 125, "PUT": 0, "TRACE": 0}, "httpstatus": {"-xx": 0, "1xx": 0, "2xx": 61836, "3xx": 10696, "4xx": 88, "5xx": 0}, "httpversion": {"HTTP/0.9": 0, "HTTP/1.0": 61436, "HTTP/1.1": 11183, "HTTP/X.X": 1}, "tothits": 72620, "transferred_bytes": 580848707, "uusers": 1912}, "1998-05-06T07:00:00.000Z": {"htmlhits": 3966, "httpmethod": {"CONNECT": 0, "DELETE": 0, "GET": 73563, "HEAD": 14, "OPTIONS": 2, "OTHER": 0, "POST": 134, "PUT": 0, "TRACE": 0}, "httpstatus": {"-xx": 0, "1xx": 0, "2xx": 64008, "3xx": 9539, "4xx": 164, "5xx": 2}, "httpversion": {"HTTP/0.9": 0, "HTTP/1.0": 62213, "HTTP/1.1": 11500, "HTTP/X.X": 0}, "tothits": 73713, "transferred_bytes": 506674261, "uusers": 1984}, "1998-05-06T08:00:00.000Z": {"htmlhits": 4198, "httpmethod": {"CONNECT": 0, "DELETE": 0, "GET": 76404, "HEAD": 114, "OPTIONS": 0, "OTHER": 0, "POST": 164, "PUT": 0, "TRACE": 0}, "httpstatus": {"-xx": 0, "1xx": 0, "2xx": 66474, "3xx": 10149, "4xx": 57, "5xx": 2}, "httpversion": {"HTTP/0.9": 0, "HTTP/1.0": 66151, "HTTP/1.1": 10531, "HTTP/X.X": 0}, "tothits": 76682, "transferred_bytes": 537405375, "uusers": 1934}, "1998-05-06T09:00:00.000Z": {"htmlhits": 4523, "httpmethod": {"CONNECT": 0, "DELETE": 0, "GET": 82178, "HEAD": 21, "OPTIONS": 0, "OTHER": 0, "POST": 204, "PUT": 0, "TRACE": 0}, "httpstatus": {"-xx": 0, "1xx": 0, "2xx": 70870, "3xx": 11453, "4xx": 79, "5xx": 1}, "httpversion": {"HTTP/0.9": 0, "HTTP/1.0": 71191, "HTTP/1.1": 11211, "HTTP/X.X": 1}, "tothits": 82403, "transferred_bytes": 564977559, "uusers": 2198}, "1998-05-06T10:00:00.000Z": {"htmlhits": 4917, "httpmethod": {"CONNECT": 0, "DELETE": 0, "GET": 90382, "HEAD": 7, "OPTIONS": 0, "OTHER": 0, "POST": 252, "PUT": 0, "TRACE": 0}, "httpstatus": {"-xx": 0, "1xx": 0, "2xx": 78877, "3xx": 11705, "4xx": 59, "5xx": 0}, "httpversion": {"HTTP/0.9": 0, "HTTP/1.0": 75398, "HTTP/1.1": 15240, "HTTP/X.X": 3}, "tothits": 90641, "transferred_bytes": 595344818, "uusers": 2250}, "1998-05-06T11:00:00.000Z": {"htmlhits": 5290, "httpmethod": {"CONNECT": 0, "DELETE": 0, "GET": 95635, "HEAD": 13, "OPTIONS": 0, "OTHER": 0, "POST": 257, "PUT": 0, "TRACE": 0}, "httpstatus": {"-xx": 0, "1xx": 0, "2xx": 83933, "3xx": 11915, "4xx": 56, "5xx": 1}, "httpversion": {"HTTP/0.9": 0, "HTTP/1.0": 80613, "HTTP/1.1": 15289, "HTTP/X.X": 3}, "tothits": 95905, "transferred_bytes": 685299307, "uusers": 2445}, "1998-05-06T12:00:00.000Z": {"htmlhits": 5790, "httpmethod": {"CONNECT": 0, "DELETE": 0, "GET": 100694, "HEAD": 19, "OPTIONS": 0, "OTHER": 0, "POST": 161, "PUT": 0, "TRACE": 0}, "httpstatus": {"-xx": 2, "1xx": 0, "2xx": 88275, "3xx": 12467, "4xx": 127, "5xx": 3}, "httpversion": {"HTTP/0.9": 0, "HTTP/1.0": 86851, "HTTP/1.1": 14014, "HTTP/X.X": 9}, "tothits": 100874, "transferred_bytes": 734039454, "uusers": 2585}, "1998-05-06T13:00:00.000Z": {"htmlhits": 5468, "httpmethod": {"CONNECT": 0, "DELETE": 0, "GET": 97487, "HEAD": 19, "OPTIONS": 0, "OTHER": 0, "POST": 207, "PUT": 0, "TRACE": 0}, "httpstatus": {"-xx": 0, "1xx": 0, "2xx": 85103, "3xx": 12527, "4xx": 82, "5xx": 1}, "httpversion": {"HTTP/0.9": 0, "HTTP/1.0": 81593, "HTTP/1.1": 16117, "HTTP/X.X": 3}, "tothits": 97713, "transferred_bytes": 623892113, "uusers": 2535}, "1998-05-06T14:00:00.000Z": {"htmlhits": 5154, "httpmethod": {"CONNECT": 0, "DELETE": 0, "GET": 95156, "HEAD": 11, "OPTIONS": 0, "OTHER": 0, "POST": 228, "PUT": 0, "TRACE": 0}, "httpstatus": {"-xx": 0, "1xx": 0, "2xx": 84015, "3xx": 11267, "4xx": 105, "5xx": 8}, "httpversion": {"HTTP/0.9": 0, "HTTP/1.0": 81039, "HTTP/1.1": 14352, "HTTP/X.X": 4}, "tothits": 95395, "transferred_bytes": 597326745, "uusers": 2451}, "1998-05-06T15:00:00.000Z": {"htmlhits": 5266, "httpmethod": {"CONNECT": 0, "DELETE": 0, "GET": 98062, "HEAD": 20, "OPTIONS": 0, "OTHER": 0, "POST": 248, "PUT": 0, "TRACE": 0}, "httpstatus": {"-xx": 0, "1xx": 0, "2xx": 86935, "3xx": 11239, "4xx": 153, "5xx": 3}, "httpversion": {"HTTP/0.9": 0, "HTTP/1.0": 80309, "HTTP/1.1": 18020, "HTTP/X.X": 1}, "tothits": 98330, "transferred_bytes": 628430139, "uusers": 2406}, "1998-05-06T16:00:00.000Z": {"htmlhits": 4699, "httpmethod": {"CONNECT": 0, "DELETE": 0, "GET": 85678, "HEAD": 15, "OPTIONS": 0, "OTHER": 0, "POST": 172, "PUT": 0, "TRACE": 0}, "httpstatus": {"-xx": 0, "1xx": 0, "2xx": 75900, "3xx": 9733, "4xx": 232, "5xx": 0}, "httpversion": {"HTTP/0.9": 0, "HTTP/1.0": 70766, "HTTP/1.1": 15094, "HTTP/X.X": 5}, "tothits": 85865, "transferred_bytes": 587418989, "uusers": 2125}, "1998-05-06T17:00:00.000Z": {"htmlhits": 4206, "httpmethod": {"CONNECT": 0, "DELETE": 0, "GET": 78074, "HEAD": 10, "OPTIONS": 0, "OTHER": 0, "POST": 137, "PUT": 0, "TRACE": 0}, "httpstatus": {"-xx": 0, "1xx": 0, "2xx": 69935, "3xx": 8230, "4xx": 56, "5xx": 0}, "httpversion": {"HTTP/0.9": 0, "HTTP/1.0": 63968, "HTTP/1.1": 14253, "HTTP/X.X": 0}, "tothits": 78221, "transferred_bytes": 459205863, "uusers": 2053}, "1998-05-06T18:00:00.000Z": {"htmlhits": 4141, "httpmethod": {"CONNECT": 0, "DELETE": 0, "GET": 74543, "HEAD": 77, "OPTIONS": 0, "OTHER": 0, "POST": 158, "PUT": 0, "TRACE": 0}, "httpstatus": {"-xx": 0, "1xx": 0, "2xx": 66236, "3xx": 8493, "4xx": 48, "5xx": 1}, "httpversion": {"HTTP/0.9": 0, "HTTP/1.0": 62357, "HTTP/1.1": 12414, "HTTP/X.X": 7}, "tothits": 74778, "transferred_bytes": 507233978, "uusers": 1886}, "1998-05-06T19:00:00.000Z": {"bytes_transferred": 444069933, "html_hits": 3522, "http_method": {"CONNECT": 0, "DELETE": 0, "GET": 67721, "HEAD": 12, "OPTIONS": 0, "OTHER": 0, "POST": 199, "PUT": 0, "TRACE": 0}, "http_status": {"-xx": 0, "1xx": 0, "2xx": 61437, "3xx": 6425, "4xx": 68, "5xx": 2}, "http_version": {"HTTP/0.9": 0, "HTTP/1.0": 53818, "HTTP/1.1": 14110, "HTTP/X.X": 4}, "total_hits": 67932, "uniq_users": 1839, "views_per_page": {"/english/download/download.html": 1, "/english/help/body.html": 8, "/english/help/site.html": 16, "/english/history/body.html": 44, "/english/history/history_of/football.html": 8, "/english/history/history_of/football_in_france.html": 9, "/english/history/history_of/the_cup.html": 12, "/english/history/past_cups/argentina78.html": 5, "/english/history/past_cups/brazil50.html": 2, "/english/history/past_cups/chile62.html": 6, "/english/history/past_cups/england66.html": 3, "/english/history/past_cups/france38.html": 4, "/english/history/past_cups/germany74.html": 3, "/english/history/past_cups/italy34.html": 3, "/english/history/past_cups/italy90.html": 2, "/english/history/past_cups/mexico70.html": 8, "/english/history/past_cups/mexico86.html": 9, "/english/history/past_cups/spain82.html": 2, "/english/history/past_cups/sweden58.html": 4, "/english/history/past_cups/switzerland54.html": 2, "/english/history/past_cups/uraguay30.html": 9, "/english/history/past_cups/usa94.html": 9, "/english/history/reading/reading.html": 2, "/english/hosts/cfo/cfo.html": 27, "/english/hosts/cfo/main.html": 3, "/english/hosts/cfo/platini.html": 1, "/english/hosts/fff/fff.html": 1, "/english/hosts/fifa/fifa.html": 3, "/english/hosts/fifa/fifa5.html": 1, "/english/hosts/fifa/fifa6.html": 1, "/english/hosts/fifa/fifa7.html": 1, "/english/hosts/sponsors/1cat0498.html": 1, "/english/hosts/sponsors/3cat0498.html": 1, "/english/hosts/suppliers/2cat0498.html": 1, "/english/hosts/suppliers/4cat0498.html": 1, "/english/hosts/suppliers/eds.html": 3, "/english/hosts/suppliers/frtelecom.html": 3, "/english/hosts/suppliers/hp.html": 3, "/english/hosts/suppliers/index1.html": 3, "/english/hosts/suppliers/index2.html": 2, "/english/hosts/suppliers/index3.html": 4, "/english/hosts/suppliers/index4.html": 1, "/english/hosts/suppliers/sybase.html": 2, "/english/index.html": 468, "/english/mascot/mascot.html": 1, "/english/member/body.html": 61, "/english/nav_inet.html": 486, "/english/nav_top_inet.html": 538, "/english/playing/body.html": 165, "/english/playing/download/download.html": 78, "/english/playing/links.html": 41, "/english/playing/mascot/about.html": 18, "/english/playing/mascot/bio.html": 6, "/english/playing/mascot/mascot.html": 76, "/english/splash_inet.html": 487, "/english/tickets/body.html": 53, "/english/tickets/faq.html": 7, "/english/tickets/faq2.html": 2, "/english/tickets/in_france.html": 5, "/english/tickets/out_france.html": 10, "/english/tickets/tck_global.html": 7, "/english/tickets/tickets_fr.html": 2, "/english/venues/accommodations.html": 6, "/english/venues/accomodations.html": 8, "/english/venues/body.html": 56, "/english/venues/cities/bordeaux.html": 1, "/english/venues/cities/lens.html": 4, "/english/venues/cities/lyon.html": 5, "/english/venues/cities/marseille.html": 8, "/english/venues/cities/montpellier.html": 2, "/english/venues/cities/nantes.html": 5, "/english/venues/cities/paris.html": 7, "/english/venues/cities/saint-denis.html": 9, "/english/venues/cities/saint-etienne.html": 7, "/english/venues/cities/toulouse.html": 1, "/english/venues/distance.html": 6, "/english/venues/france.html": 10, "/english/venues/venues/bordeaux.html": 2, "/english/venues/venues/marseille.html": 2, "/english/venues/venues/montpellier.html": 2, "/english/venues/venues/nantes.html": 1, "/english/venues/venues/paris.html": 3, "/english/venues/venues/saint-denis.html": 1, "/english/venues/venues/saint-etienne.html": 2, "/english/welcoming/suppliers/laposte.html": 1, "/french/bienvenue/news/mousepad.html": 1, "/french/help/site.html": 3, "/french/history/body.html": 13, "/french/history/history_of/the_cup.html": 1, "/french/history/past_cups/brazil50.html": 1, "/french/history/past_cups/germany74.html": 1, "/french/history/past_cups/mexico70.html": 1, "/french/history/past_cups/mexico86.html": 1, "/french/history/past_cups/spain82.html": 2, "/french/history/past_cups/sweden58.html": 1, "/french/history/past_cups/uraguay30.html": 1, "/french/history/past_cups/usa94.html": 1, "/french/hosts/cfo/cfo.html": 4, "/french/hosts/fff/competitions.html": 1, "/french/hosts/fifa/fifa3.html": 1, "/french/hosts/fifa/fifa6.html": 1, "/french/hosts/sponsors/3cat0498.html": 1, "/french/hosts/suppliers/4cat0498.html": 1, "/french/index.html": 119, "/french/member/body.html": 12, "/french/nav_inet.html": 111, "/french/nav_top_inet.html": 111, "/french/playing/body.html": 16, "/french/playing/download/download.html": 8, "/french/playing/links.html": 9, "/french/playing/mascot/about.html": 3, "/french/playing/mascot/bio.html": 3, "/french/playing/mascot/mascot.html": 16, "/french/splash_inet.html": 112, "/french/tickets/body.html": 9, "/french/tickets/faq.html": 1, "/french/tickets/in_france.html": 2, "/french/tickets/in_france3.html": 1, "/french/tickets/out_france.html": 2, "/french/tickets/tck_global.html": 4, "/french/venues/accomodations.html": 2, "/french/venues/body.html": 18, "/french/venues/cities/marseille.html": 2, "/french/venues/cities/paris.html": 1, "/french/venues/cities/saint-denis.html": 4, "/french/venues/cities/saint-etienne.html": 1, "/french/venues/cities/toulouse.html": 1, "/french/venues/distance.html": 4, "/french/venues/france.html": 1, "/french/venues/venues/bordeaux.html": 3, "/french/venues/venues/marseille.html": 1, "/french/venues/venues/paris.html": 2, "/french/venues/venues/saint-denis.html": 1, "/french/venues/venues/saint-etienne.html": 1, "/french/venues/venues/toulouse.html": 1, "/german/index.html": 1, "/index.html": 3, "/legal.html": 3, "/spanish/index.html": 3}}}